LICENSE
MANIFEST.in
README.rst
setup.py
tree.xml
./__init__.py
./tree.py
./tree.xml
./tryton.cfg
./locale/de_DE.po
./tests/__init__.py
./tests/test_tree.py
./view/product_form.xml
./view/product_node_list.xml
./view/product_node_tree.xml
./view/tree_node_form.xml
./view/tree_node_list.xml
./view/tree_node_tree.xml
./view/website_view_form.xml
locale/de_DE.po
trytond_nereid_catalog_tree.egg-info/PKG-INFO
trytond_nereid_catalog_tree.egg-info/SOURCES.txt
trytond_nereid_catalog_tree.egg-info/dependency_links.txt
trytond_nereid_catalog_tree.egg-info/entry_points.txt
trytond_nereid_catalog_tree.egg-info/not-zip-safe
trytond_nereid_catalog_tree.egg-info/requires.txt
trytond_nereid_catalog_tree.egg-info/top_level.txt
view/product_form.xml
view/product_node_list.xml
view/product_node_tree.xml
view/tree_node_form.xml
view/tree_node_list.xml
view/tree_node_tree.xml
view/website_view_form.xml